{
    "schede": {
        "Schede Bianche": "15",
        "Schede Nulle": "8",
        "Schede Contestate": "0"
    },
    "liste": [
        {
            "nome": "ACTEA",
            "voti_totali": 69
        },
        {
            "nome": "NIKE",
            "voti_totali": 32
        },
        {
            "nome": "UNIVERSITÀ POPOLARE",
            "voti_totali": 13
        },
        {
            "nome": "DMI INSIDER",
            "voti_totali": 189
        }
    ],
    "eletti": [
        {
            "nominativo": "MARROCCIA Marco",
            "voti": "22",
            "lista": "ACTEA"
        },
        {
            "nominativo": "PISTORIO Anna",
            "voti": "24",
            "lista": "ACTEA"
        },
        {
            "nominativo": "PERRONE Carla",
            "voti": "30",
            "lista": "NIKE"
        },
        {
            "nominativo": "CATANIA Valentina",
            "voti": "8",
            "lista": "UNIVERSITÀ POPOLARE"
        },
        {
            "nominativo": "PECORAIO Pierpaolo",
            "voti": "16",
            "lista": "DMI INSIDER"
        },
        {
            "nominativo": "BORZI' Stefano",
            "voti": "64",
            "lista": "DMI INSIDER"
        },
        {
            "nominativo": "CATANIA Lorenzo",
            "voti": "31",
            "lista": "DMI INSIDER"
        },
        {
            "nominativo": "STECCANELLA Luca",
            "voti": "8",
            "lista": "DMI INSIDER"
        },
        {
            "nominativo": "SCIUTO Rita",
            "voti": "30",
            "lista": "DMI INSIDER"
        },
        {
            "nominativo": "MARINO Salvatore",
            "voti": "10",
            "lista": "DMI INSIDER"
        }
    ],
    "non_eletti": [
        {
            "nominativo": "DRAGA' Federica",
            "voti": "15",
            "lista": "ACTEA"
        },
        {
            "nominativo": "CASTIGLIONE Gianpietro",
            "voti": "0",
            "lista": "UNIVERSITÀ POPOLARE"
        },
        {
            "nominativo": "SCIACCA Susanna",
            "voti": "0",
            "lista": "UNIVERSITÀ POPOLARE"
        },
        {
            "nominativo": "PIAZZA Alessio",
            "voti": "7",
            "lista": "DMI INSIDER"
        },
        {
            "nominativo": "DI PATTI Stefano",
            "voti": "0",
            "lista": "DMI INSIDER"
        },
        {
            "nominativo": "NASO ONOFRIO Giuseppe",
            "voti": "0",
            "lista": "DMI INSIDER"
        }
    ],
    "seggi_da_assegnare": "10",
    "dipartimento": "MATEMATICA E INFORMATICA",
    "quoziente": "30,3",
    "votanti": "326",
    "perc_votanti": "31,44",
    "elettori": "1037"
}