{
    "schede": {
        "Schede Bianche": "9",
        "Schede Nulle": "10",
        "Schede Contestate": "0"
    },
    "liste": [
        {
            "nome": "IL FUTURO DELLA SCIENZA ‐ CONTROCAMPUS",
            "voti_totali": 152
        },
        {
            "nome": "NUCLEO ATTIVO",
            "voti_totali": 152
        },
        {
            "nome": "ALLEANZA UNIVERSITARIA",
            "voti_totali": 104
        }
    ],
    "eletti": [
        {
            "nominativo": "MILIA Manuela",
            "voti": "23",
            "lista": "IL FUTURO DELLA SCIENZA ‐ CONTROCAMPUS"
        },
        {
            "nominativo": "DISTEFANO Alessia",
            "voti": "17",
            "lista": "NUCLEO ATTIVO"
        },
        {
            "nominativo": "TOMASELLA Pascal",
            "voti": "37",
            "lista": "NUCLEO ATTIVO"
        },
        {
            "nominativo": "GRASSO Alessandro",
            "voti": "36",
            "lista": "NUCLEO ATTIVO"
        },
        {
            "nominativo": "VELLA Andrea",
            "voti": "40",
            "lista": "ALLEANZA UNIVERSITARIA"
        },
        {
            "nominativo": "CARBONARO Antonino Biagio",
            "voti": "23",
            "lista": "ALLEANZA UNIVERSITARIA"
        }
    ],
    "non_eletti": [
        {
            "nominativo": "GIUFFRIDA Federico",
            "voti": "14",
            "lista": "NUCLEO ATTIVO"
        },
        {
            "nominativo": "BONACCI Paolo Giuseppe",
            "voti": "0",
            "lista": "NUCLEO ATTIVO"
        },
        {
            "nominativo": "FABIANO Luigi",
            "voti": "16",
            "lista": "NUCLEO ATTIVO"
        },
        {
            "nominativo": "SICALI Luciano Amedeo",
            "voti": "22",
            "lista": "ALLEANZA UNIVERSITARIA"
        },
        {
            "nominativo": "GRANATA Sharon",
            "voti": "4",
            "lista": "ALLEANZA UNIVERSITARIA"
        }
    ],
    "seggi_da_assegnare": "6",
    "dipartimento": "SCIENZE CHIMICHE",
    "quoziente": "47,3333",
    "votanti": "303",
    "perc_votanti": "42,80",
    "elettori": "708"
}